restructuredpython/cload.py
restructuredpython/tempload.py
restructuredpython/__init__.py
restructuredpython/restructuredpython.py
restructuredpython/parser.py
restructuredpython/check_syntax.py
restructuredpython/predefined/__init__.py
restructuredpython/predefined/decorators.py
restructuredpython/predefined/decorators/logging.py
restructuredpython/predefined/decorators/strict_types.py
restructuredpython/predefined/decorators/timer.py
restructuredpython/predefined/decorators/memoization.py
restructuredpython/predefined/decorators/retry.py
restructuredpython/predefined/decorators/access_control.py
restructuredpython/predefined/subinterpreter/optimize.py
restructuredpython/predefined/subinterpreter/__init__.py
restructuredpython/lib/io.c
restructuredpython/api/libio.cpython-314-darwin.so
restructuredpython-2.6.0.dist-info/RECORD
restructuredpython-2.6.0.dist-info/WHEEL
restructuredpython-2.6.0.dist-info/entry_points.txt
restructuredpython-2.6.0.dist-info/top_level.txt
restructuredpython-2.6.0.dist-info/METADATA
restructuredpython-2.6.0.dist-info/licenses/LICENSE
