Metadata-Version: 2.4
Name: restructuredpython
Version: 2.6.0
Summary: A superset of Python with many new features, including full JS integration, multiline comments, header files, and optional curly brackets around control statements
Author-email: Rihaan Meher <meherrihaan@gmail.com>
License: Apache-2.0
Project-URL: Homepage, https://restructuredpython.rf.gd
Project-URL: Documentation, https://restructuredpython.readthedocs.org
Project-URL: Repository, https://github.com/sharktide/restructuredpython.git
Project-URL: Issues, https://github.com/sharktide/restructuredpython/issues
Project-URL: Changelog, https://restructuredpython.readthedocs.io/en/latest/changelog.html
Classifier: Programming Language :: Python :: 3
Classifier: Programming Language :: Python :: 3.10
Classifier: Programming Language :: Python :: 3.11
Classifier: Programming Language :: Python :: 3.12
Classifier: Programming Language :: Python :: 3.13
Requires-Python: >=3.10
License-File: LICENSE
Requires-Dist: textfmt
Dynamic: license-file
